outcome_surveys/__init__.py
outcome_surveys/apps.py
outcome_surveys/constants.py
outcome_surveys/models.py
outcome_surveys/signals.py
outcome_surveys/surveymonkey_client.py
outcome_surveys/urls.py
outcome_surveys/management/__init__.py
outcome_surveys/management/commands/__init__.py
outcome_surveys/management/commands/import_survey_data.py
outcome_surveys/management/commands/send_follow_up_segment_events_for_passed_learners.py
outcome_surveys/management/commands/send_learning_time_achieved_segment_events.py
outcome_surveys/management/commands/tests/__init__.py
outcome_surveys/management/commands/tests/mock_responses.py
outcome_surveys/management/commands/tests/test_import_survey_data.py
outcome_surveys/management/commands/tests/test_send_follow_up_segment_events_for_passed_learners.py
outcome_surveys/management/commands/tests/test_send_learning_time_achieved_segment_events.py
outcome_surveys/migrations/0001_initial.py
outcome_surveys/migrations/0002_learnercourseevent_already_sent.py
outcome_surveys/migrations/0003_auto_20230130_0352.py
outcome_surveys/migrations/0004_auto_20230203_0147.py
outcome_surveys/migrations/0005_auto_20230220_0433.py
outcome_surveys/migrations/0006_alter_learnercourseevent_event_type.py
outcome_surveys/migrations/__init__.py
outcome_surveys/templates/outcome_surveys/base.html
outcome_surveys-3.0.3.dist-info/licenses/LICENSE.txt
outcome_surveys-3.0.3.dist-info/METADATA
outcome_surveys-3.0.3.dist-info/WHEEL
outcome_surveys-3.0.3.dist-info/entry_points.txt
outcome_surveys-3.0.3.dist-info/top_level.txt
outcome_surveys-3.0.3.dist-info/RECORD
