Metadata-Version: 2.4
Name: outcome-surveys
Version: 3.0.3
Summary: An edx-platform plugin to send and track course events.
Home-page: https://github.com/edx/outcome-surveys
Author: edX
Author-email: oscm@edx.org
License: AGPL 3.0
Keywords: Python edx
Classifier: Development Status :: 3 - Alpha
Classifier: Framework :: Django
Classifier: Framework :: Django :: 4.2
Classifier: Intended Audience :: Developers
Classifier: License :: OSI Approved :: GNU Affero General Public License v3 or later (AGPLv3+)
Classifier: Natural Language :: English
Classifier: Programming Language :: Python :: 3
Classifier: Programming Language :: Python :: 3.11
Requires-Python: >=3.11
License-File: LICENSE.txt
Requires-Dist: Django
Requires-Dist: django-model-utils
Requires-Dist: edx-django-utils
Requires-Dist: edx-opaque-keys
Requires-Dist: jsonfield
Requires-Dist: requests
Requires-Dist: snowflake-connector-python
Dynamic: author
Dynamic: author-email
Dynamic: classifier
Dynamic: description
Dynamic: home-page
Dynamic: keywords
Dynamic: license
Dynamic: license-file
Dynamic: requires-dist
Dynamic: requires-python
Dynamic: summary
